caffeinated_whale_cli/__init__.py
caffeinated_whale_cli/main.py
caffeinated_whale_cli/commands/__init__.py
caffeinated_whale_cli/commands/backup.py
caffeinated_whale_cli/commands/config.py
caffeinated_whale_cli/commands/init.py
caffeinated_whale_cli/commands/inspect.py
caffeinated_whale_cli/commands/list.py
caffeinated_whale_cli/commands/logs.py
caffeinated_whale_cli/commands/open.py
caffeinated_whale_cli/commands/restart.py
caffeinated_whale_cli/commands/restore.py
caffeinated_whale_cli/commands/rm.py
caffeinated_whale_cli/commands/run.py
caffeinated_whale_cli/commands/start.py
caffeinated_whale_cli/commands/status.py
caffeinated_whale_cli/commands/stop.py
caffeinated_whale_cli/commands/unlock.py
caffeinated_whale_cli/commands/update.py
caffeinated_whale_cli/commands/utils.py
caffeinated_whale_cli/commands/where.py
caffeinated_whale_cli/utils/__init__.py
caffeinated_whale_cli/utils/auto_inspect.py
caffeinated_whale_cli/utils/cache.py
caffeinated_whale_cli/utils/completion_utils.py
caffeinated_whale_cli/utils/config_utils.py
caffeinated_whale_cli/utils/console.py
caffeinated_whale_cli/utils/db_utils.py
caffeinated_whale_cli/utils/docker_utils.py
caffeinated_whale_cli/utils/port_utils.py
caffeinated_whale_cli/utils/sendme_utils.py
caffeinated_whale_cli/utils/startup.py
caffeinated_whale_cli/utils/tips.py
caffeinated_whale_cli/utils/vscode_utils.py
caffeinated_whale_cli-0.28.0.dist-info/METADATA
caffeinated_whale_cli-0.28.0.dist-info/WHEEL
caffeinated_whale_cli-0.28.0.dist-info/entry_points.txt
caffeinated_whale_cli-0.28.0.dist-info/top_level.txt
caffeinated_whale_cli-0.28.0.dist-info/RECORD
